{
  "version": "5.0.1",
  "flags": {},
  "shapes": [
    {
      "label": "h",
      "points": [
        [
          635.1768798828125,
          718.77294921875
        ],
        [
          752.9910888671875,
          745.991943359375
        ],
        [
          741.9417724609375,
          793.8177490234375
        ],
        [
          624.1275634765625,
          766.5987548828125
        ]
      ],
      "group_id": null,
      "shape_type": "polygon",
      "flags": {}
    },
    {
      "label": "h",
      "points": [
        [
          426.7934265136719,
          679.0530395507812
        ],
        [
          543.8133544921875,
          674.5447387695312
        ],
        [
          545.8590087890625,
          727.6425170898438
        ],
        [
          428.83905029296875,
          732.1508178710938
        ]
      ],
      "group_id": null,
      "shape_type": "polygon",
      "flags": {}
    },
    {
      "label": "h",
      "points": [
        [
          1263.827392578125,
          995.6692504882812
        ],
        [
          1328.208740234375,
          891.2615356445312
        ],
        [
          1373.443603515625,
          919.1549682617188
        ],
        [
          1309.062255859375,
          1023.5626831054688
        ]
      ],
      "group_id": null,
      "shape_type": "polygon",
      "flags": {}
    },
    {
      "label": "h",
      "points": [
        [
          359.6426696777344,
          772.4293823242188
        ],
        [
          427.0231018066406,
          701.3242797851562
        ],
        [
          459.5950012207031,
          732.1900024414062
        ],
        [
          392.2145690917969,
          803.2951049804688
        ]
      ],
      "group_id": null,
      "shape_type": "polygon",
      "flags": {}
    },
    {
      "label": "h",
      "points": [
        [
          445.7542419433594,
          374.5433044433594
        ],
        [
          516.8826293945312,
          443.8133239746094
        ],
        [
          481.1639709472656,
          480.4902648925781
        ],
        [
          410.03558349609375,
          411.2202453613281
        ]
      ],
      "group_id": null,
      "shape_type": "polygon",
      "flags": {}
    },
    {
      "label": "h",
      "points": [
        [
          912.387451171875,
          41.649566650390625
        ],
        [
          1038.923095703125,
          52.26228332519531
        ],
        [
          1034.7431640625,
          102.0987548828125
        ],
        [
          908.20751953125,
          91.48603820800781
        ]
      ],
      "group_id": null,
      "shape_type": "polygon",
      "flags": {}
    },
    {
      "label": "h",
      "points": [
        [
          1230.53564453125,
          270.4623718261719
        ],
        [
          1342.64453125,
          292.7186584472656
        ],
        [
          1331.806640625,
          347.3106994628906
        ],
        [
          1219.69775390625,
          325.0544128417969
        ]
      ],
      "group_id": null,
      "shape_type": "polygon",
      "flags": {}
    },
    {
      "label": "h",
      "points": [
        [
          292.85986328125,
          502.7621154785156
        ],
        [
          392.73687744140625,
          524.1195068359375
        ],
        [
          382.17138671875,
          573.5286865234375
        ],
        [
          282.29437255859375,
          552.1712646484375
        ]
      ],
      "group_id": null,
      "shape_type": "polygon",
      "flags": {}
    },
    {
      "label": "h",
      "points": [
        [
          612.5666511632219,
          962.1058519580696
        ],
        [
          623.8367927647844,
          839.5300462940071
        ],
        [
          695.9112556554094,
          846.1568773486946
        ],
        [
          684.6411140538469,
          968.7326830127571
        ]
      ],
      "group_id": null,
      "shape_type": "polygon",
      "flags": {}
    },
    {
      "label": "h",
      "points": [
        [
          975.5481567382812,
          1078.87890625
        ],
        [
          998.933349609375,
          967.69189453125
        ],
        [
          1056.202392578125,
          979.73681640625
        ],
        [
          1032.817138671875,
          1090.923828125
        ]
      ],
      "group_id": null,
      "shape_type": "polygon",
      "flags": {}
    },
    {
      "label": "h",
      "points": [
        [
          617.2911392405063,
          843.0379746835442
        ],
        [
          570.4556962025316,
          849.367088607595
        ],
        [
          580.5822784810126,
          979.746835443038
        ],
        [
          617.2911392405063,
          978.4810126582278
        ]
      ],
      "group_id": null,
      "shape_type": "polygon",
      "flags": {}
    },
    {
      "label": "h",
      "points": [
        [
          895.3157894736842,
          62.73684210526315
        ],
        [
          795.3157894736842,
          3.526315789473685
        ]
      ],
      "group_id": null,
      "shape_type": "rectangle",
      "flags": {}
    },
    {
      "label": "b",
      "points": [
        [
          647.9473684210526,
          41.68421052631579
        ],
        [
          565.0526315789474,
          -0.4210526315789478
        ]
      ],
      "group_id": null,
      "shape_type": "rectangle",
      "flags": {}
    },
    {
      "label": "h",
      "points": [
        [
          1416.3684210526317,
          1108.7894736842104
        ],
        [
          1355.842105263158,
          1191.6842105263158
        ]
      ],
      "group_id": null,
      "shape_type": "rectangle",
      "flags": {}
    }
  ],
  "imagePath": "132_132_20220810_105917.bmp",
  "imageData": null,
  "imageHeight": 1200,
  "imageWidth": 1920
}