{
  "version": "5.0.1",
  "flags": {},
  "shapes": [
    {
      "label": "h",
      "points": [
        [
          1533.683837890625,
          83.13533782958984
        ],
        [
          1651.659423828125,
          -2.393167495727539
        ],
        [
          1686.56103515625,
          45.749000549316406
        ],
        [
          1568.58544921875,
          131.2775115966797
        ]
      ],
      "group_id": null,
      "shape_type": "polygon",
      "flags": {}
    },
    {
      "label": "mashkook salem",
      "points": [
        [
          369.3698425292969,
          601.3167114257812
        ],
        [
          480.1170349121094,
          546.9199829101562
        ],
        [
          505.1332092285156,
          597.8507690429688
        ],
        [
          394.3860168457031,
          652.2474975585938
        ]
      ],
      "group_id": null,
      "shape_type": "polygon",
      "flags": {}
    },
    {
      "label": "mashkook salem",
      "points": [
        [
          873.8888549804688,
          422.509521484375
        ],
        [
          994.6621704101562,
          391.47589111328125
        ],
        [
          1008.4015502929688,
          444.9454345703125
        ],
        [
          887.6282348632812,
          475.97906494140625
        ]
      ],
      "group_id": null,
      "shape_type": "polygon",
      "flags": {}
    },
    {
      "label": "h",
      "points": [
        [
          196.95372009277344,
          271.2225341796875
        ],
        [
          298.7876892089844,
          345.53009033203125
        ],
        [
          270.6092529296875,
          384.14697265625
        ],
        [
          168.7752685546875,
          309.83941650390625
        ]
      ],
      "group_id": null,
      "shape_type": "polygon",
      "flags": {}
    },
    {
      "label": "h",
      "points": [
        [
          460.2073974609375,
          421.58099365234375
        ],
        [
          541.445068359375,
          354.03729248046875
        ],
        [
          571.9061279296875,
          390.674072265625
        ],
        [
          490.66845703125,
          458.2177734375
        ]
      ],
      "group_id": null,
      "shape_type": "polygon",
      "flags": {}
    },
    {
      "label": "h",
      "points": [
        [
          1690.20361328125,
          956.2474365234375
        ],
        [
          1761.18408203125,
          1038.3367919921875
        ],
        [
          1724.4248046875,
          1070.1217041015625
        ],
        [
          1653.4443359375,
          988.0323486328125
        ]
      ],
      "group_id": null,
      "shape_type": "polygon",
      "flags": {}
    },
    {
      "label": "h",
      "points": [
        [
          1382.201904296875,
          306.0845642089844
        ],
        [
          1458.893310546875,
          407.7081604003906
        ],
        [
          1418.033935546875,
          438.5432434082031
        ],
        [
          1341.342529296875,
          336.9196472167969
        ]
      ],
      "group_id": null,
      "shape_type": "polygon",
      "flags": {}
    },
    {
      "label": "h",
      "points": [
        [
          1454.4473876953125,
          -2.737916946411133
        ],
        [
          1552.3529052734375,
          24.63368034362793
        ],
        [
          1537.3240966796875,
          78.39017486572266
        ],
        [
          1439.4185791015625,
          51.018577575683594
        ]
      ],
      "group_id": null,
      "shape_type": "polygon",
      "flags": {}
    },
    {
      "label": "mashkook kharab",
      "points": [
        [
          631.7715454101562,
          1038.7279052734375
        ],
        [
          716.4735717773438,
          1106.8941650390625
        ],
        [
          685.8353881835938,
          1144.9644775390625
        ],
        [
          601.1333618164062,
          1076.7982177734375
        ]
      ],
      "group_id": null,
      "shape_type": "polygon",
      "flags": {}
    },
    {
      "label": "h",
      "points": [
        [
          739.7547607421875,
          152.2445831298828
        ],
        [
          830.650146484375,
          145.98719787597656
        ],
        [
          834.324462890625,
          199.3616180419922
        ],
        [
          743.4290771484375,
          205.61900329589844
        ]
      ],
      "group_id": null,
      "shape_type": "polygon",
      "flags": {}
    },
    {
      "label": "h",
      "points": [
        [
          1235.4837646484375,
          512.835693359375
        ],
        [
          1262.0548095703125,
          392.79986572265625
        ],
        [
          1310.1317138671875,
          403.44219970703125
        ],
        [
          1283.5606689453125,
          523.47802734375
        ]
      ],
      "group_id": null,
      "shape_type": "polygon",
      "flags": {}
    },
    {
      "label": "h",
      "points": [
        [
          1105.011962890625,
          500.9730224609375
        ],
        [
          1139.95947265625,
          616.2821044921875
        ],
        [
          1084.176025390625,
          633.188720703125
        ],
        [
          1049.228515625,
          517.879638671875
        ]
      ],
      "group_id": null,
      "shape_type": "polygon",
      "flags": {}
    },
    {
      "label": "h",
      "points": [
        [
          1721.1944580078125,
          554.4900512695312
        ],
        [
          1734.9632568359375,
          660.7134399414062
        ],
        [
          1681.4935302734375,
          667.6442260742188
        ],
        [
          1667.7247314453125,
          561.4208374023438
        ]
      ],
      "group_id": null,
      "shape_type": "polygon",
      "flags": {}
    },
    {
      "label": "h",
      "points": [
        [
          1534.57763671875,
          1177.6053466796875
        ],
        [
          1560.56982421875,
          1052.8221435546875
        ],
        [
          1623.871826171875,
          1066.0079345703125
        ],
        [
          1597.879638671875,
          1190.7911376953125
        ]
      ],
      "group_id": null,
      "shape_type": "polygon",
      "flags": {}
    },
    {
      "label": "mashkook salem",
      "points": [
        [
          1445.8111572265625,
          381.57623291015625
        ],
        [
          1444.4771728515625,
          274.01507568359375
        ],
        [
          1497.5062255859375,
          273.35736083984375
        ],
        [
          1498.8402099609375,
          380.91851806640625
        ]
      ],
      "group_id": null,
      "shape_type": "polygon",
      "flags": {}
    },
    {
      "label": "b",
      "points": [
        [
          1425.578947368421,
          57.473684210526315
        ],
        [
          1366.3684210526317,
          -5.684210526315789
        ]
      ],
      "group_id": null,
      "shape_type": "rectangle",
      "flags": {}
    },
    {
      "label": "b",
      "points": [
        [
          1282.157894736842,
          1157.4736842105262
        ],
        [
          1378.2105263157894,
          1195.6315789473683
        ]
      ],
      "group_id": null,
      "shape_type": "rectangle",
      "flags": {}
    },
    {
      "label": "b",
      "points": [
        [
          1678.2105263157894,
          1121.9473684210527
        ],
        [
          1626.8947368421052,
          1195.6315789473683
        ]
      ],
      "group_id": null,
      "shape_type": "rectangle",
      "flags": {}
    },
    {
      "label": "b",
      "points": [
        [
          286.10526315789474,
          1093.0
        ],
        [
          186.10526315789474,
          1175.8947368421052
        ]
      ],
      "group_id": null,
      "shape_type": "rectangle",
      "flags": {}
    },
    {
      "label": "b",
      "points": [
        [
          603.2105263157895,
          1125.8947368421052
        ],
        [
          700.578947368421,
          1187.7368421052631
        ]
      ],
      "group_id": null,
      "shape_type": "rectangle",
      "flags": {}
    }
  ],
  "imagePath": "235_235_20220810_110111.bmp",
  "imageData": null,
  "imageHeight": 1200,
  "imageWidth": 1920
}