{
  "version": "5.0.1",
  "flags": {},
  "shapes": [
    {
      "label": "h",
      "points": [
        [
          273.58148193359375,
          541.6305541992188
        ],
        [
          352.204833984375,
          446.2752990722656
        ],
        [
          396.00775146484375,
          482.39215087890625
        ],
        [
          317.3843994140625,
          577.7474365234375
        ]
      ],
      "group_id": null,
      "shape_type": "polygon",
      "flags": {}
    },
    {
      "label": "h",
      "points": [
        [
          686.794189453125,
          780.807861328125
        ],
        [
          785.9478759765625,
          866.005859375
        ],
        [
          744.4228515625,
          914.332763671875
        ],
        [
          645.2691650390625,
          829.134765625
        ]
      ],
      "group_id": null,
      "shape_type": "polygon",
      "flags": {}
    },
    {
      "label": "h",
      "points": [
        [
          1081.73828125,
          316.8573303222656
        ],
        [
          1167.837158203125,
          397.9224548339844
        ],
        [
          1130.6396484375,
          437.4297790527344
        ],
        [
          1044.540771484375,
          356.3646545410156
        ]
      ],
      "group_id": null,
      "shape_type": "polygon",
      "flags": {}
    },
    {
      "label": "h",
      "points": [
        [
          455.94793701171875,
          496.0096130371094
        ],
        [
          562.8009033203125,
          543.6082153320312
        ],
        [
          543.7241821289062,
          586.4329833984375
        ],
        [
          436.8712158203125,
          538.8344116210938
        ]
      ],
      "group_id": null,
      "shape_type": "polygon",
      "flags": {}
    },
    {
      "label": "h",
      "points": [
        [
          302.9081115722656,
          676.6626586914062
        ],
        [
          402.5455627441406,
          680.0319213867188
        ],
        [
          400.9585876464844,
          726.9625854492188
        ],
        [
          301.3211364746094,
          723.5933227539062
        ]
      ],
      "group_id": null,
      "shape_type": "polygon",
      "flags": {}
    },
    {
      "label": "h",
      "points": [
        [
          1538.070556640625,
          491.1959533691406
        ],
        [
          1598.891357421875,
          609.670654296875
        ],
        [
          1545.479736328125,
          637.0904541015625
        ],
        [
          1484.658935546875,
          518.61572265625
        ]
      ],
      "group_id": null,
      "shape_type": "polygon",
      "flags": {}
    },
    {
      "label": "mashkook salem",
      "points": [
        [
          1088.2497760696917,
          529.1840209960938
        ],
        [
          1157.5127155228167,
          627.7040405273438
        ],
        [
          1115.9990436478167,
          656.8895874023438
        ],
        [
          1046.7361041946917,
          558.3695678710938
        ]
      ],
      "group_id": null,
      "shape_type": "polygon",
      "flags": {}
    },
    {
      "label": "h",
      "points": [
        [
          866.5486450195312,
          281.30694580078125
        ],
        [
          925.3361206054688,
          355.79425048828125
        ],
        [
          887.4577026367188,
          385.68902587890625
        ],
        [
          828.6702270507812,
          311.20172119140625
        ]
      ],
      "group_id": null,
      "shape_type": "polygon",
      "flags": {}
    },
    {
      "label": "h",
      "points": [
        [
          1472.474853515625,
          1021.4812622070312
        ],
        [
          1570.94287109375,
          1091.4302978515625
        ],
        [
          1535.25439453125,
          1141.669189453125
        ],
        [
          1436.786376953125,
          1071.7200927734375
        ]
      ],
      "group_id": null,
      "shape_type": "polygon",
      "flags": {}
    },
    {
      "label": "w",
      "points": [
        [
          309.227783203125,
          614.8267211914062
        ],
        [
          366.18914794921875,
          561.9680786132812
        ],
        [
          399.19189453125,
          597.5324096679688
        ],
        [
          342.23052978515625,
          650.3910522460938
        ]
      ],
      "group_id": null,
      "shape_type": "polygon",
      "flags": {}
    },
    {
      "label": "h",
      "points": [
        [
          1778.3287353515625,
          626.5916748046875
        ],
        [
          1824.1141357421875,
          732.4930419921875
        ],
        [
          1768.1346435546875,
          756.6951904296875
        ],
        [
          1722.3492431640625,
          650.7938232421875
        ]
      ],
      "group_id": null,
      "shape_type": "polygon",
      "flags": {}
    },
    {
      "label": "h",
      "points": [
        [
          1569.8023681640625,
          946.1077270507812
        ],
        [
          1596.8907470703125,
          1079.25341796875
        ],
        [
          1543.2086181640625,
          1090.175048828125
        ],
        [
          1516.1202392578125,
          957.029296875
        ]
      ],
      "group_id": null,
      "shape_type": "polygon",
      "flags": {}
    },
    {
      "label": "b",
      "points": [
        [
          561.1052631578947,
          39.05263157894737
        ],
        [
          491.36842105263156,
          -0.4210526315789478
        ]
      ],
      "group_id": null,
      "shape_type": "rectangle",
      "flags": {}
    },
    {
      "label": "h",
      "points": [
        [
          1405.842105263158,
          1125.8947368421052
        ],
        [
          1284.7894736842104,
          1190.3684210526317
        ]
      ],
      "group_id": null,
      "shape_type": "rectangle",
      "flags": {}
    }
  ],
  "imagePath": "58_58_20220810_105857.bmp",
  "imageData": null,
  "imageHeight": 1200,
  "imageWidth": 1920
}