{
  "version": "5.0.1",
  "flags": {},
  "shapes": [
    {
      "label": "w",
      "points": [
        [
          248.94161987304688,
          122.26866149902344
        ],
        [
          336.6139831542969,
          48.43562698364258
        ],
        [
          362.9314270019531,
          79.68605041503906
        ],
        [
          275.2590637207031,
          153.5190887451172
        ]
      ],
      "group_id": null,
      "shape_type": "polygon",
      "flags": {}
    },
    {
      "label": "w",
      "points": [
        [
          812.2442016601562,
          885.7935180664062
        ],
        [
          881.6149291992188,
          789.7717895507812
        ],
        [
          917.7069702148438,
          815.8463745117188
        ],
        [
          848.3362426757812,
          911.8681030273438
        ]
      ],
      "group_id": null,
      "shape_type": "polygon",
      "flags": {}
    },
    {
      "label": "w",
      "points": [
        [
          314.139892578125,
          799.6105346679688
        ],
        [
          410.36907958984375,
          775.4000854492188
        ],
        [
          419.9644775390625,
          813.5388793945312
        ],
        [
          323.73529052734375,
          837.7493286132812
        ]
      ],
      "group_id": null,
      "shape_type": "polygon",
      "flags": {}
    },
    {
      "label": "w",
      "points": [
        [
          766.1801147460938,
          151.0208282470703
        ],
        [
          834.6307983398438,
          208.37940979003906
        ],
        [
          810.0296020507812,
          237.7380828857422
        ],
        [
          741.5789184570312,
          180.37950134277344
        ]
      ],
      "group_id": null,
      "shape_type": "polygon",
      "flags": {}
    },
    {
      "label": "w",
      "points": [
        [
          958.5005493164062,
          804.5670776367188
        ],
        [
          1070.3739013671875,
          835.6766967773438
        ],
        [
          1056.676025390625,
          884.9360961914062
        ],
        [
          944.8026123046875,
          853.8264770507812
        ]
      ],
      "group_id": null,
      "shape_type": "polygon",
      "flags": {}
    },
    {
      "label": "w",
      "points": [
        [
          530.47607421875,
          728.3204956054688
        ],
        [
          565.0364990234375,
          832.8724975585938
        ],
        [
          527.46728515625,
          845.2913208007812
        ],
        [
          492.9068603515625,
          740.7393188476562
        ]
      ],
      "group_id": null,
      "shape_type": "polygon",
      "flags": {}
    },
    {
      "label": "w",
      "points": [
        [
          153.8721923828125,
          417.5704040527344
        ],
        [
          164.02392578125,
          293.0334777832031
        ],
        [
          216.98306274414062,
          297.3504943847656
        ],
        [
          206.83132934570312,
          421.8874206542969
        ]
      ],
      "group_id": null,
      "shape_type": "polygon",
      "flags": {}
    },
    {
      "label": "w",
      "points": [
        [
          939.407470703125,
          954.272705078125
        ],
        [
          1038.391845703125,
          975.7474365234375
        ],
        [
          1019.1011962890625,
          1064.6646728515625
        ],
        [
          920.1168212890625,
          1043.18994140625
        ]
      ],
      "group_id": null,
      "shape_type": "polygon",
      "flags": {}
    },
    {
      "label": "w",
      "points": [
        [
          132.95669555664062,
          15.282955169677734
        ],
        [
          230.58102416992188,
          42.672386169433594
        ],
        [
          206.59637451171875,
          128.1610565185547
        ],
        [
          108.9720458984375,
          100.7716293334961
        ]
      ],
      "group_id": null,
      "shape_type": "polygon",
      "flags": {}
    }
  ],
  "imagePath": "214_214_20220810_095807.bmp",
  "imageData": null,
  "imageHeight": 1200,
  "imageWidth": 1920
}