{
  "version": "5.0.1",
  "flags": {},
  "shapes": [
    {
      "label": "half kharab",
      "points": [
        [
          903.5023803710938,
          702.6826782226562
        ],
        [
          1009.9006958007812,
          756.6748657226562
        ],
        [
          991.8506469726562,
          792.2448120117188
        ],
        [
          885.4523315429688,
          738.2526245117188
        ]
      ],
      "group_id": null,
      "shape_type": "polygon",
      "flags": {}
    },
    {
      "label": "w",
      "points": [
        [
          430.4710998535156,
          1008.1061401367188
        ],
        [
          566.1083984375,
          1021.3163452148438
        ],
        [
          561.4691162109375,
          1068.9501953125
        ],
        [
          425.831787109375,
          1055.739990234375
        ]
      ],
      "group_id": null,
      "shape_type": "polygon",
      "flags": {}
    },
    {
      "label": "half kharab",
      "points": [
        [
          1291.5546875,
          141.16139221191406
        ],
        [
          1408.889892578125,
          144.89149475097656
        ],
        [
          1407.23681640625,
          196.89292907714844
        ],
        [
          1289.901611328125,
          193.16282653808594
        ]
      ],
      "group_id": null,
      "shape_type": "polygon",
      "flags": {}
    },
    {
      "label": "w",
      "points": [
        [
          434.9216613769531,
          270.2067565917969
        ],
        [
          533.1864013671875,
          347.9985046386719
        ],
        [
          506.9924011230469,
          381.0862121582031
        ],
        [
          408.7276611328125,
          303.2944641113281
        ]
      ],
      "group_id": null,
      "shape_type": "polygon",
      "flags": {}
    },
    {
      "label": "w",
      "points": [
        [
          1411.8726806640625,
          203.9045867919922
        ],
        [
          1469.1107177734375,
          295.1965026855469
        ],
        [
          1434.4788818359375,
          316.909912109375
        ],
        [
          1377.2408447265625,
          225.61801147460938
        ]
      ],
      "group_id": null,
      "shape_type": "polygon",
      "flags": {}
    },
    {
      "label": "w",
      "points": [
        [
          1126.7716064453125,
          669.6454467773438
        ],
        [
          1231.1329345703125,
          705.5440063476562
        ],
        [
          1214.0606689453125,
          755.1754760742188
        ],
        [
          1109.6993408203125,
          719.2769165039062
        ]
      ],
      "group_id": null,
      "shape_type": "polygon",
      "flags": {}
    },
    {
      "label": "w",
      "points": [
        [
          948.677734375,
          1042.5260009765625
        ],
        [
          1025.645263671875,
          1133.6597900390625
        ],
        [
          993.017333984375,
          1161.2159423828125
        ],
        [
          916.0498046875,
          1070.0821533203125
        ]
      ],
      "group_id": null,
      "shape_type": "polygon",
      "flags": {}
    },
    {
      "label": "w",
      "points": [
        [
          427.9537048339844,
          117.99919891357422
        ],
        [
          526.102783203125,
          147.95025634765625
        ],
        [
          514.1961669921875,
          186.96807861328125
        ],
        [
          416.04705810546875,
          157.01702880859375
        ]
      ],
      "group_id": null,
      "shape_type": "polygon",
      "flags": {}
    },
    {
      "label": "w",
      "points": [
        [
          1012.589599609375,
          485.69659423828125
        ],
        [
          1053.341064453125,
          569.2986450195312
        ],
        [
          994.3359375,
          598.0604858398438
        ],
        [
          953.58447265625,
          514.4584350585938
        ]
      ],
      "group_id": null,
      "shape_type": "polygon",
      "flags": {}
    },
    {
      "label": "w",
      "points": [
        [
          1402.142578125,
          883.1246337890625
        ],
        [
          1412.01171875,
          986.059326171875
        ],
        [
          1348.7568359375,
          992.1240234375
        ],
        [
          1338.8876953125,
          889.1893310546875
        ]
      ],
      "group_id": null,
      "shape_type": "polygon",
      "flags": {}
    },
    {
      "label": "b",
      "points": [
        [
          805.8421052631579,
          7.473684210526315
        ],
        [
          888.7368421052631,
          -3.0526315789473686
        ]
      ],
      "group_id": null,
      "shape_type": "rectangle",
      "flags": {}
    }
  ],
  "imagePath": "117_117_20220810_075723.bmp",
  "imageData": null,
  "imageHeight": 1200,
  "imageWidth": 1920
}