{
  "version": "5.0.1",
  "flags": {},
  "shapes": [
    {
      "label": "w",
      "points": [
        [
          648.7180239408837,
          1056.6171598614387
        ],
        [
          746.2602602690087,
          1150.7519254864387
        ],
        [
          713.0175844877587,
          1185.1979704083137
        ],
        [
          615.4753481596337,
          1091.0632047833137
        ]
      ],
      "group_id": null,
      "shape_type": "polygon",
      "flags": {}
    },
    {
      "label": "mashkook kharab",
      "points": [
        [
          582.5449288191196,
          643.0876735298933
        ],
        [
          658.2053292097446,
          732.7240260689558
        ],
        [
          624.1178047956821,
          761.4967311470808
        ],
        [
          548.4574044050571,
          671.8603786080183
        ]
      ],
      "group_id": null,
      "shape_type": "polygon",
      "flags": {}
    },
    {
      "label": "w",
      "points": [
        [
          845.091064453125,
          625.7201538085938
        ],
        [
          927.4991455078125,
          550.8246459960938
        ],
        [
          966.1490478515625,
          593.3513793945312
        ],
        [
          883.740966796875,
          668.2468872070312
        ]
      ],
      "group_id": null,
      "shape_type": "polygon",
      "flags": {}
    },
    {
      "label": "w",
      "points": [
        [
          1159.39892578125,
          1123.591552734375
        ],
        [
          1208.68994140625,
          1017.2255859375
        ],
        [
          1255.2880859375,
          1038.819580078125
        ],
        [
          1205.9970703125,
          1145.185546875
        ]
      ],
      "group_id": null,
      "shape_type": "polygon",
      "flags": {}
    },
    {
      "label": "w",
      "points": [
        [
          218.1680145263672,
          958.0940551757812
        ],
        [
          264.42724609375,
          866.8619995117188
        ],
        [
          313.30609130859375,
          891.6460571289062
        ],
        [
          267.046875,
          982.8781127929688
        ]
      ],
      "group_id": null,
      "shape_type": "polygon",
      "flags": {}
    },
    {
      "label": "w",
      "points": [
        [
          1482.0640869140625,
          1045.3026123046875
        ],
        [
          1523.9656982421875,
          1140.7730712890625
        ],
        [
          1458.8577880859375,
          1169.3487548828125
        ],
        [
          1416.9561767578125,
          1073.8782958984375
        ]
      ],
      "group_id": null,
      "shape_type": "polygon",
      "flags": {}
    },
    {
      "label": "w",
      "points": [
        [
          300.69512939453125,
          53.040977478027344
        ],
        [
          366.03773584905656,
          45.283018867924525
        ],
        [
          416.964599609375,
          32.230308532714844
        ],
        [
          427.52752685546875,
          91.2457046508789
        ],
        [
          311.258056640625,
          112.0563735961914
        ]
      ],
      "group_id": null,
      "shape_type": "polygon",
      "flags": {}
    },
    {
      "label": "w",
      "points": [
        [
          924.9994506835938,
          382.65234375
        ],
        [
          987.7412719726562,
          380.1163330078125
        ],
        [
          989.1984252929688,
          416.165771484375
        ],
        [
          926.4566040039062,
          418.7017822265625
        ]
      ],
      "group_id": null,
      "shape_type": "polygon",
      "flags": {}
    },
    {
      "label": "w",
      "points": [
        [
          1221.117431640625,
          626.5565795898438
        ],
        [
          1319.982177734375,
          629.6406860351562
        ],
        [
          1317.544189453125,
          707.7942504882812
        ],
        [
          1218.679443359375,
          704.7101440429688
        ]
      ],
      "group_id": null,
      "shape_type": "polygon",
      "flags": {}
    },
    {
      "label": "w",
      "points": [
        [
          1254.961181640625,
          1066.9205322265625
        ],
        [
          1351.2099609375,
          1084.0484619140625
        ],
        [
          1337.591552734375,
          1160.5765380859375
        ],
        [
          1241.3427734375,
          1143.4486083984375
        ]
      ],
      "group_id": null,
      "shape_type": "polygon",
      "flags": {}
    },
    {
      "label": "w",
      "points": [
        [
          310.10595703125,
          641.5571899414062
        ],
        [
          344.4378662109375,
          530.3660278320312
        ],
        [
          425.34130859375,
          555.3461303710938
        ],
        [
          391.0093994140625,
          666.5372924804688
        ]
      ],
      "group_id": null,
      "shape_type": "polygon",
      "flags": {}
    },
    {
      "label": "b",
      "points": [
        [
          1045.3157894736842,
          68.0
        ],
        [
          1121.6315789473683,
          -7.0
        ]
      ],
      "group_id": null,
      "shape_type": "rectangle",
      "flags": {}
    },
    {
      "label": "b",
      "points": [
        [
          1450.578947368421,
          90.36842105263158
        ],
        [
          1497.9473684210527,
          -3.0526315789473686
        ]
      ],
      "group_id": null,
      "shape_type": "rectangle",
      "flags": {}
    },
    {
      "label": "b",
      "points": [
        [
          1491.3684210526317,
          93.0
        ],
        [
          1559.7894736842104,
          -1.7368421052631575
        ]
      ],
      "group_id": null,
      "shape_type": "rectangle",
      "flags": {}
    },
    {
      "label": "b",
      "points": [
        [
          308.4736842105263,
          54.8421052631579
        ],
        [
          383.4736842105263,
          -7.0
        ]
      ],
      "group_id": null,
      "shape_type": "rectangle",
      "flags": {}
    },
    {
      "label": "b",
      "points": [
        [
          784.7894736842105,
          1141.6842105263158
        ],
        [
          721.6315789473684,
          1181.157894736842
        ]
      ],
      "group_id": null,
      "shape_type": "rectangle",
      "flags": {}
    }
  ],
  "imagePath": "188_188_20220810_080545.bmp",
  "imageData": null,
  "imageHeight": 1200,
  "imageWidth": 1920
}