{
  "version": "5.0.1",
  "flags": {},
  "shapes": [
    {
      "label": "mashkook salem",
      "points": [
        [
          802.4205932617188,
          950.8573608398438
        ],
        [
          918.4890747070312,
          883.2566528320312
        ],
        [
          942.9334106445312,
          925.2268676757812
        ],
        [
          826.8649291992188,
          992.8275756835938
        ]
      ],
      "group_id": null,
      "shape_type": "polygon",
      "flags": {}
    },
    {
      "label": "h",
      "points": [
        [
          916.254150390625,
          863.3258666992188
        ],
        [
          1044.288818359375,
          850.6710815429688
        ],
        [
          1050.034912109375,
          908.8074340820312
        ],
        [
          922.000244140625,
          921.4622192382812
        ]
      ],
      "group_id": null,
      "shape_type": "polygon",
      "flags": {}
    },
    {
      "label": "h",
      "points": [
        [
          810.4898071289062,
          494.42657470703125
        ],
        [
          920.6691284179688,
          497.80914306640625
        ],
        [
          919.1437377929688,
          547.4943237304688
        ],
        [
          808.9644165039062,
          544.1117553710938
        ]
      ],
      "group_id": null,
      "shape_type": "polygon",
      "flags": {}
    },
    {
      "label": "h",
      "points": [
        [
          1128.6910400390625,
          917.4437255859375
        ],
        [
          1218.5384521484375,
          923.6092529296875
        ],
        [
          1215.5076904296875,
          967.7742919921875
        ],
        [
          1125.6602783203125,
          961.6087646484375
        ]
      ],
      "group_id": null,
      "shape_type": "polygon",
      "flags": {}
    },
    {
      "label": "h",
      "points": [
        [
          958.2504272460938,
          949.9390869140625
        ],
        [
          997.7357788085938,
          1043.0101318359375
        ],
        [
          946.7534790039062,
          1064.6392822265625
        ],
        [
          907.2681274414062,
          971.5682373046875
        ]
      ],
      "group_id": null,
      "shape_type": "polygon",
      "flags": {}
    },
    {
      "label": "h",
      "points": [
        [
          707.5505981445312,
          1061.54541015625
        ],
        [
          739.1946411132812,
          955.927001953125
        ],
        [
          795.1188354492188,
          972.6822509765625
        ],
        [
          763.4747924804688,
          1078.3006591796875
        ]
      ],
      "group_id": null,
      "shape_type": "polygon",
      "flags": {}
    },
    {
      "label": "h",
      "points": [
        [
          806.142822265625,
          927.7421875
        ],
        [
          807.9393310546875,
          813.8717041015625
        ],
        [
          859.216796875,
          814.6806640625
        ],
        [
          857.4202880859375,
          928.5511474609375
        ]
      ],
      "group_id": null,
      "shape_type": "polygon",
      "flags": {}
    },
    {
      "label": "h",
      "points": [
        [
          1004.0030517578125,
          1071.12353515625
        ],
        [
          1013.4041748046875,
          961.2587890625
        ],
        [
          1059.8905029296875,
          965.236572265625
        ],
        [
          1050.4893798828125,
          1075.101318359375
        ]
      ],
      "group_id": null,
      "shape_type": "polygon",
      "flags": {}
    }
  ],
  "imagePath": "111_111_20220810_110811.bmp",
  "imageData": null,
  "imageHeight": 1200,
  "imageWidth": 1920
}