{
  "version": "5.0.1",
  "flags": {},
  "shapes": [
    {
      "label": "h",
      "points": [
        [
          984.5537719726562,
          508.0771179199219
        ],
        [
          1112.10986328125,
          532.0274658203125
        ],
        [
          1101.568359375,
          588.169921875
        ],
        [
          974.01220703125,
          564.2196044921875
        ]
      ],
      "group_id": null,
      "shape_type": "polygon",
      "flags": {}
    },
    {
      "label": "h",
      "points": [
        [
          326.75634765625,
          635.8204345703125
        ],
        [
          451.252197265625,
          621.0439453125
        ],
        [
          458.1695556640625,
          679.3245849609375
        ],
        [
          333.6737060546875,
          694.10107421875
        ]
      ],
      "group_id": null,
      "shape_type": "polygon",
      "flags": {}
    },
    {
      "label": "mashkook salem",
      "points": [
        [
          856.2294311523438,
          220.53028869628906
        ],
        [
          986.4345092773438,
          222.9921417236328
        ],
        [
          985.4617309570312,
          274.443603515625
        ],
        [
          855.2566528320312,
          271.98175048828125
        ]
      ],
      "group_id": null,
      "shape_type": "polygon",
      "flags": {}
    },
    {
      "label": "h",
      "points": [
        [
          1119.2169189453125,
          -12.472570419311523
        ],
        [
          1244.7418212890625,
          22.524818420410156
        ],
        [
          1225.6966552734375,
          90.83385467529297
        ],
        [
          1100.1717529296875,
          55.836463928222656
        ]
      ],
      "group_id": null,
      "shape_type": "polygon",
      "flags": {}
    },
    {
      "label": "h",
      "points": [
        [
          821.4487915039062,
          772.3551635742188
        ],
        [
          921.4662475585938,
          828.6465454101562
        ],
        [
          892.8491821289062,
          879.4928588867188
        ],
        [
          792.8317260742188,
          823.2014770507812
        ]
      ],
      "group_id": null,
      "shape_type": "polygon",
      "flags": {}
    },
    {
      "label": "h",
      "points": [
        [
          811.532470703125,
          451.77911376953125
        ],
        [
          852.8011474609375,
          351.6282958984375
        ],
        [
          897.473876953125,
          370.036376953125
        ],
        [
          856.2052001953125,
          470.18719482421875
        ]
      ],
      "group_id": null,
      "shape_type": "polygon",
      "flags": {}
    },
    {
      "label": "h",
      "points": [
        [
          1191.349609375,
          79.40530395507812
        ],
        [
          1301.13427734375,
          74.31080627441406
        ],
        [
          1303.611083984375,
          127.68289184570312
        ],
        [
          1193.826416015625,
          132.7773895263672
        ]
      ],
      "group_id": null,
      "shape_type": "polygon",
      "flags": {}
    },
    {
      "label": "h",
      "points": [
        [
          839.2410888671875,
          512.6611938476562
        ],
        [
          874.1961669921875,
          627.8936157226562
        ],
        [
          824.5184326171875,
          642.9630737304688
        ],
        [
          789.5633544921875,
          527.7306518554688
        ]
      ],
      "group_id": null,
      "shape_type": "polygon",
      "flags": {}
    },
    {
      "label": "b",
      "points": [
        [
          759.7894736842105,
          31.157894736842103
        ],
        [
          649.2631578947369,
          0.8947368421052628
        ]
      ],
      "group_id": null,
      "shape_type": "rectangle",
      "flags": {}
    },
    {
      "label": "b",
      "points": [
        [
          805.8421052631579,
          25.89473684210526
        ],
        [
          911.1052631578947,
          0.8947368421052628
        ]
      ],
      "group_id": null,
      "shape_type": "rectangle",
      "flags": {}
    },
    {
      "label": "b",
      "points": [
        [
          1346.6315789473683,
          62.73684210526315
        ],
        [
          1266.3684210526317,
          -3.0526315789473686
        ]
      ],
      "group_id": null,
      "shape_type": "rectangle",
      "flags": {}
    },
    {
      "label": "b",
      "points": [
        [
          776.8947368421052,
          1145.6315789473683
        ],
        [
          846.6315789473684,
          1185.1052631578948
        ]
      ],
      "group_id": null,
      "shape_type": "rectangle",
      "flags": {}
    }
  ],
  "imagePath": "168_168_20220810_110947.bmp",
  "imageData": null,
  "imageHeight": 1200,
  "imageWidth": 1920
}